{"updated_at": "2026-05-22 16:36 UTC", "total": 150, "articles": [{"id": 1, "url": "https://www.axismag.jp/posts/2026/05/710344.html", "title": "「只是打電話」的孩子專用電話。排除螢幕的通訊裝置「Tin Can（提恩肯）」", "orig_title": "“ただ通話するだけ”の子ども向け電話。スクリーンを排したコミュニケーション端末「Tin Canティン・キャン）」 | AXIS Web | デザインの視点で、人間の可能性や創造性を伝えるメディア", "published": "2026-05-20 13:52", "ym": "2026-05", "category": "product", "cat_label": "產品 Product"}, {"id": 2, "url": "https://www.axismag.jp/posts/2026/05/710701.html", "title": "喚醒水的記憶的黃金色展館。H&P Architects，「The Source：Ashui Pavilion 2026」 | AXIS Web | 以設計觀點傳遞人類可能性與創造性的媒體", "orig_title": "水の記憶を呼び起こす黄金色のパビリオン。H&P Architects、「ザ・ソース：アシュイ・パビリオン2026」 | AXIS Web | デザインの視点で、人間の可能性や創造性を伝えるメディア", "published": "2026-05-20 13:37", "ym": "2026-05", "category": "architecture", "cat_label": "建築 Architecture"}, {"id": 3, "url": "https://www.axismag.jp/posts/2026/05/711212.html", "title": "為平面設計注入「時間」的概念。於ggg舉辦「井口皓太 動態圖像設計」| AXIS Web | 以設計的視角，傳遞人類的可能性與創造力之媒體", "orig_title": "グラフィックに“時間”の概念を。gggで「井口皓太 モーショングラフィックス」開催 | AXIS Web | デザインの視点で、人間の可能性や創造性を伝えるメディア", "published": "2026-05-20 10:07", "ym": "2026-05", "category": "graphic", "cat_label": "圖像 Graphic"}, {"id": 4, "url": "https://www.axismag.jp/posts/2026/05/709813.html", "title": "以功能導向收納工具與資財的DEWALT（得偉）。擴充Garage Accessories系列", "orig_title": "ツールや資材を機能的に収納するDEWALT（デウォルト）。 ガレージアクセサリーシリーズを拡充 | AXIS Web | デザインの視点で、人間の可能性や創造性を伝えるメディア", "published": "2026-05-19 13:10", "ym": "2026-05", "category": "product", "cat_label": "產品 Product"}, {"id": 5, "url": "https://www.axismag.jp/posts/2026/05/710815.html", "title": "將液體的流動注入眼鏡。JINS推出與湯瑪斯・赫茲威克的首款聯名商品", "orig_title": "液体の流れをアイウエアに。JINS、トーマス・ヘザウィックとの初のコラボアイテムを発売 | AXIS Web | デザインの視点で、人間の可能性や創造性を伝えるメディア", "published": "2026-05-18 16:19", "ym": "2026-05", "category": "product", "cat_label": "產品 Product"}, {"id": 6, "url": "https://www.axismag.jp/posts/2026/05/710414.html", "title": "「美」能成為抗爭嗎？多麗絲・范・諾頓基金會於威尼斯舉辦首展", "orig_title": "「美」は抗議になり得るのか。ドリス・ヴァン・ノッテン財団、初の展覧会をヴェネツィアで開催 | AXIS Web | デザインの視点で、人間の可能性や創造性を伝えるメディア", "published": "2026-05-18 12:38", "ym": "2026-05", "category": "art", "cat_label": "藝術 Art"}, {"id": 7, "url": "https://www.axismag.jp/posts/2026/05/710328.html", "title": "漆器與蒔繪裝飾的「初期國產平台鋼琴」。山葉，成功完成120年前文化資產鋼琴的修復工作 | AXIS Web | 以設計視角傳達人類可能性與創造力的媒體", "orig_title": "漆と蒔絵装飾の“初期国産グランドピアノ” 。ヤマハ、120年以上前の文化財ピアノ修理を完了 | AXIS Web | デザインの視点で、人間の可能性や創造性を伝えるメディア", "published": "2026-05-14 18:23", "ym": "2026-05", "category": "technology", "cat_label": "科技 Technology"}, {"id": 8, "url": "https://www.axismag.jp/posts/2026/05/709488.html", "title": "芬蘭最長最高的橋梁。專為行人與自行車設計的「克魯努沃里橋」正式開通 | AXIS Web | 以設計觀點傳遞人類可能性與創造力的媒體", "orig_title": "フィンランドで、最も長く最も高い橋。 歩行者、自転車向けの「クルーヌヴオリ橋」開通 | AXIS Web | デザインの視点で、人間の可能性や創造性を伝えるメディア", "published": "2026-05-14 15:08", "ym": "2026-05", "category": "business", "cat_label": "商業 Business"}, {"id": 9, "url": "https://www.axismag.jp/posts/2026/05/710398.html", "title": "「作為『看不見的結構』的玻璃家具」——清澄白河舉辦「玻璃家具展」", "orig_title": "“見えない構造”としてのガラス家具。清澄白河で「ガラスの家具展」開催 | AXIS Web | デザインの視点で、人間の可能性や創造性を伝えるメディア", "published": "2026-05-14 10:31", "ym": "2026-05", "category": "product", "cat_label": "產品 Product"}, {"id": 10, "url": "https://www.axismag.jp/posts/2026/05/708814.html", "title": "將若冲的圖像融入日常。福田美術館推出展覽限定原創商品", "orig_title": "若冲のモチーフを日常へ。福田美術館、展覧会オリジナルグッズを展開 | AXIS Web | デザインの視点で、人間の可能性や創造性を伝えるメディア", "published": "2026-05-13 13:48", "ym": "2026-05", "category": "product", "cat_label": "產品 Product"}, {"id": 11, "url": "https://www.axismag.jp/posts/2026/05/710145.html", "title": "走訪城市街巷，遇見經典名椅。都市漫遊型設計展「名作椅子的遠征」| AXIS Web | 以設計視角傳遞人類可能性與創造性的媒體", "orig_title": "街を巡りながら名作椅子と出会う。都市回遊型デザイン展「名作椅子のエクスペディション」 | AXIS Web | デザインの視点で、人間の可能性や創造性を伝えるメディア", "published": "2026-05-13 09:50", "ym": "2026-05", "category": "product", "cat_label": "產品 Product"}, {"id": 12, "url": "https://www.axismag.jp/posts/2026/05/704634.html", "title": "將「披裹光芒」的體驗化為香氣。ISSEY MIYAKE PARFUMS，全新作品「LUMIÈRE de ISSEY」", "orig_title": "「光をまとう」という体験を香りに。ISSEY MIYAKE PARFUMS、新作「ルミエールドゥ イッセイ」 | AXIS Web | デザインの視点で、人間の可能性や創造性を伝えるメディア", "published": "2026-05-11 16:39", "ym": "2026-05", "category": "fashion", "cat_label": "時尚 Fashion"}, {"id": 13, "url": "https://www.axismag.jp/posts/2026/05/709946.html", "title": "引導都市昆蟲的人工花朵。在大氣污染下運作的授粉導航系統「Faux Flora」 | AXIS Web | 以設計觀點傳達人類可能性與創造力的媒體", "orig_title": "都市の昆虫を導く人工の花。大気汚染下で機能する受粉ナビゲーション「フォーフローラ（Faux Flora）」 | AXIS Web | デザインの視点で、人間の可能性や創造性を伝えるメディア", "published": "2026-05-11 15:54", "ym": "2026-05", "category": "product", "cat_label": "產品 Product"}, {"id": 14, "url": "https://www.axismag.jp/posts/2026/05/708232.html", "title": "以與SANAA建築對話的形式進行擴張。OMA操刀設計的紐約新美術館新館落成 | AXIS Web | 以設計觀點傳遞人類可能性與創造性的媒體", "orig_title": "SANAAの建築と対話するかたちで拡張。OMAによるニューミュージアム新館が完成 | AXIS Web | デザインの視点で、人間の可能性や創造性を伝えるメディア", "published": "2026-05-08 15:04", "ym": "2026-05", "category": "architecture", "cat_label": "建築 Architecture"}, {"id": 15, "url": "https://www.axismag.jp/posts/2026/05/709997.html", "title": "個展「Just by | だけ しか たった」重新編輯。設計師三澤 遙，發行作品集 | AXIS Web | 以設計觀點傳達人類可能性與創造性的媒體", "orig_title": "個展「Just by | だけ しか たった」を再編集。デザイナー三澤 遥、作品集を刊行 | AXIS Web | デザインの視点で、人間の可能性や創造性を伝えるメディア", "published": "2026-05-08 14:35", "ym": "2026-05", "category": "product", "cat_label": "產品 Product"}, {"id": 16, "url": "https://www.axismag.jp/posts/2026/05/709292.html", "title": "歷史建築與現代素材交會的空間。ISSEY MIYAKE於紐約開設新旗艦店", "orig_title": "歴史的建築と現代素材が交差する空間。ISSEY MIYAKE、ニューヨークに新旗艦店をオープン | AXIS Web | デザインの視点で、人間の可能性や創造性を伝えるメディア", "published": "2026-05-07 13:06", "ym": "2026-05", "category": "interior", "cat_label": "室內 Interior"}, {"id": 17, "url": "https://www.axismag.jp/posts/2026/05/708916.html", "title": "建築的「觀看」的另一種形式。瀧本幹也，發行國立西洋美術館寫真集", "orig_title": "建築を「見る」ためのもう一つの形式。瀧本幹也、国立西洋美術館の写真集を刊行 | AXIS Web | デザインの視点で、人間の可能性や創造性を伝えるメディア", "published": "2026-05-01 10:21", "ym": "2026-05", "category": "art", "cat_label": "藝術 Art"}, {"id": 18, "url": "https://www.axismag.jp/posts/2026/05/709797.html", "title": "可體驗循環型設計的兒童耳機 Morrama: Kibu 循環型耳機 | AXIS Web | 以設計觀點傳達人類可能性與創造性的媒體", "orig_title": "循環型デザインを体験できる子ども向けヘッドホン Morrama: Kibu Circular Headphones | AXIS Web | デザインの視点で、人間の可能性や創造性を伝えるメディア", "published": "2026-04-30 16:49", "ym": "2026-04", "category": "technology", "cat_label": "科技 Technology"}, {"id": 19, "url": "https://www.axismag.jp/posts/2026/05/709769.html", "title": "生活在身旁的穿戴式AI，擁有「眼」與「耳」——Looki：Looki L1 | AXIS Web | 以設計視角傳達人類可能性與創造力的媒體", "orig_title": "暮らしのそばに、“ 目”と“ 耳”を持つウェアラブルAI Looki: Looki L1 | AXIS Web | デザインの視点で、人間の可能性や創造性を伝えるメディア", "published": "2026-04-30 16:46", "ym": "2026-04", "category": "product", "cat_label": "產品 Product"}, {"id": 20, "url": "https://www.axismag.jp/posts/2026/05/709740.html", "title": "implement）「感性」的終極未來型移動工具 Sony Honda Mobility: AFEELA 1", "orig_title": "「感性」を実装する究極の未来型モビリティ Sony Honda Mobility: AFEELA 1 | AXIS Web | デザインの視点で、人間の可能性や創造性を伝えるメディア", "published": "2026-04-30 16:40", "ym": "2026-04", "category": "product", "cat_label": "產品 Product"}, {"id": 21, "url": "https://www.axismag.jp/posts/2026/04/708930.html", "title": "承載建築思想的家具──喬治亞・巴瓦復刻家具展，於神戶舉辦", "orig_title": "建築思想を宿す家具。ジェフリー・バワの復刻家具展、神戸で開催 | AXIS Web | デザインの視点で、人間の可能性や創造性を伝えるメディア", "published": "2026-04-30 16:32", "ym": "2026-04", "category": "architecture", "cat_label": "建築 Architecture"}, {"id": 22, "url": "https://www.axismag.jp/posts/2026/05/709704.html", "title": "回到攝影行為原點的「盒子」Sigma: Sigma BF | AXIS Web | 以設計的觀點，傳遞人類的可能性與創造力的媒體", "orig_title": "写真という営みの原点に還る「箱」 Sigma: Sigma BF | AXIS Web | デザインの視点で、人間の可能性や創造性を伝えるメディア", "published": "2026-04-30 16:29", "ym": "2026-04", "category": "product", "cat_label": "產品 Product"}, {"id": 23, "url": "https://www.axismag.jp/posts/2026/04/709651.html", "title": "讓身心重新站起的拐杖", "orig_title": "身体と心が立ち上がる杖 Karimoku Furniture: UP | AXIS Web | デザインの視点で、人間の可能性や創造性を伝えるメディア", "published": "2026-04-30 16:17", "ym": "2026-04", "category": "interior", "cat_label": "室內 Interior"}, {"id": 24, "url": "https://www.axismag.jp/posts/2026/04/709633.html", "title": "觸發直覺與本能、以無限形貌變化的照明 Flos: Maap", "orig_title": "直感と本能を触発し、無限に形を変えていく照明 Flos: Maap | AXIS Web | デザインの視点で、人間の可能性や創造性を伝えるメディア", "published": "2026-04-30 16:11", "ym": "2026-04", "category": "interior", "cat_label": "室內 Interior"}, {"id": 25, "url": "https://www.axismag.jp/posts/2026/04/709612.html", "title": "跨越日常的牆，也跨越內心的牆的移動載具 TOYOTA: walk me | AXIS Web | 以設計視角傳達人類可能性與創造力的媒體", "orig_title": "日常の壁を越え、心の壁も越えるモビリティへ TOYOTA: walk me | AXIS Web | デザインの視点で、人間の可能性や創造性を伝えるメディア", "published": "2026-04-30 16:07", "ym": "2026-04", "category": "product", "cat_label": "產品 Product"}, {"id": 26, "url": "https://www.axismag.jp/posts/2026/04/707093.html", "title": "以宇宙開發為靈感的機械式時計。AMIDA發表「DIGITREND NASA Tribute」| AXIS Web | 以設計觀點傳達人類可能性與創造力的媒體", "orig_title": "宇宙開発に着想を得た機械式時計。AMIDA、「DIGITREND NASA Tribute」を発表 | AXIS Web | デザインの視点で、人間の可能性や創造性を伝えるメディア", "published": "2026-04-28 14:08", "ym": "2026-04", "category": "product", "cat_label": "產品 Product"}, {"id": 27, "url": "https://www.axismag.jp/posts/2026/04/708481.html", "title": "皇居三之丸尚藏館開放前率先公開高精細複製。國寶若沖《動植綵繪》與永德《唐獅子圖屏風》。| AXIS Web | 以設計觀點傳遞人類可能性與創造性的媒體", "orig_title": "皇居三の丸尚蔵館オープンに先駆け高精細複製公開。 国宝の若沖「動植綵絵」と永徳「唐獅子図屏風」。 | AXIS Web | デザインの視点で、人間の可能性や創造性を伝えるメディア", "published": "2026-04-27 14:06", "ym": "2026-04", "category": "technology", "cat_label": "科技 Technology"}, {"id": 28, "url": "https://www.axismag.jp/posts/2026/04/709153.html", "title": "將速克達重新定義為生活風格服飾——Yamaha發動機「Fazzio」", "orig_title": "スクーターをライフスタイルウェアとして再定義 ヤマハ発動機「Fazzio」 | AXIS Web | デザインの視点で、人間の可能性や創造性を伝えるメディア", "published": "2026-04-27 10:27", "ym": "2026-04", "category": "product", "cat_label": "產品 Product"}, {"id": 29, "url": "https://www.axismag.jp/posts/2026/04/708465.html", "title": "邁向水都東京。三井不動產「Nihonbashi e-LINER」全電動船定期航運啟動 | AXIS Web | 以設計觀點傳遞人類可能性與創造性的媒體", "orig_title": "東京を水都へ。フル電動船 三井不動産「Nihonbashi e-LINER」定期運航開始 | AXIS Web | デザインの視点で、人間の可能性や創造性を伝えるメディア", "published": "2026-04-24 15:10", "ym": "2026-04", "category": "business", "cat_label": "商業 Business"}, {"id": 30, "url": "https://www.axismag.jp/posts/2026/04/706651.html", "title": "遠離「意義」而崛起的表現形式——世田谷美術館「田中信太郎展」", "orig_title": "「意味」から距離をとることで立ち上がる表現。世田谷美術館で「田中信太郎展」開催 | AXIS Web | デザインの視点で、人間の可能性や創造性を伝えるメディア", "published": "2026-04-23 16:06", "ym": "2026-04", "category": "art", "cat_label": "藝術 Art"}, {"id": 31, "url": "https://www.axismag.jp/posts/2026/04/708451.html", "title": "海藻誕生的可剝離接著劑「LOOPGLUE」。we+、博展、セメダイン共同開發 | AXIS Web | 以設計觀點傳達人類可能性與創造力的媒體", "orig_title": "海藻から生まれた剥がせる接着剤「LOOPGLUE」。 we+、博展、セメダインが共同開発 | AXIS Web | デザインの視点で、人間の可能性や創造性を伝えるメディア", "published": "2026-04-23 11:24", "ym": "2026-04", "category": "product", "cat_label": "產品 Product"}, {"id": 32, "url": "https://www.axismag.jp/posts/2026/04/708158.html", "title": "將「消除的行為」轉化為體驗。PLUS「AIRIN 富士山橡皮擦」", "orig_title": "「消す行為」を体験へと転換する。プラス「エアイン 富士山消しゴム」 | AXIS Web | デザインの視点で、人間の可能性や創造性を伝えるメディア", "published": "2026-04-23 09:19", "ym": "2026-04", "category": "product", "cat_label": "產品 Product"}, {"id": 33, "url": "https://www.axismag.jp/posts/2026/04/706371.html", "title": "從緣側發想的迦納裝置藝術「Limbo Engawa」", "orig_title": "縁側から発想したガーナのインスタレーション「Limbo Engawa」 | AXIS Web | デザインの視点で、人間の可能性や創造性を伝えるメディア", "published": "2026-04-20 14:08", "ym": "2026-04", "category": "architecture", "cat_label": "建築 Architecture"}, {"id": 34, "url": "https://www.axismag.jp/posts/2026/04/708162.html", "title": "京都・HOSOO GALLERY舉辦「塞斯特·蓋茲：光輝法衣」展覽會 | AXIS Web | 以設計觀點傳達人類可能性與創造性的媒體", "orig_title": "京都・HOSOO GALLERYで「シアスター・ゲイツ：Glorious Robe」展が開催中 | AXIS Web | デザインの視点で、人間の可能性や創造性を伝えるメディア", "published": "2026-04-20 12:58", "ym": "2026-04", "category": "art", "cat_label": "藝術 Art"}, {"id": 35, "url": "https://www.axismag.jp/posts/2026/04/708023.html", "title": "【米蘭家具展2026預覽】INDIGO Geometry of Light — INDIGO Design Collection | AXIS Web | 以設計視角傳遞人類可能性與創造力的媒體", "orig_title": "【ミラノサローネ2026プレビュー】INDIGO Geometry of Light — INDIGO Design Collection | AXIS Web | デザインの視点で、人間の可能性や創造性を伝えるメディア", "published": "2026-04-20 10:52", "ym": "2026-04", "category": "", "cat_label": ""}, {"id": 36, "url": "https://www.axismag.jp/posts/2026/04/707936.html", "title": "「共感共創」這項思想的可視化——KOKUYO舉辦設計大獎展覽", "orig_title": "「共感共創」という思想を可視化する。コクヨ、デザインアワード展を開催 | AXIS Web | デザインの視点で、人間の可能性や創造性を伝えるメディア", "published": "2026-04-17 07:58", "ym": "2026-04", "category": "product", "cat_label": "產品 Product"}, {"id": 37, "url": "https://www.axismag.jp/posts/2026/04/705186.html", "title": "基礎設施能否成為「風景」？將送電鐵塔化為地標的「Austrian Power Giants」 | AXIS Web | 以設計的觀點，傳達人類可能性與創造性的媒體", "orig_title": "インフラは“風景”になりうるか。送電鉄塔をランドマーク化する「Austrian Power Giants」 | AXIS Web | デザインの視点で、人間の可能性や創造性を伝えるメディア", "published": "2026-04-16 15:00", "ym": "2026-04", "category": "business", "cat_label": "商業 Business"}, {"id": 38, "url": "https://www.axismag.jp/posts/2026/04/707450.html", "title": "【米蘭家具展2026搶先看】RYOTA YOKOZEKI STUDIO From Flat | AXIS Web | 以設計觀點傳達人類的可能性與創造力的媒體", "orig_title": "【ミラノサローネ2026プレビュー】RYOTA YOKOZEKI STUDIO From Flat | AXIS Web | デザインの視点で、人間の可能性や創造性を伝えるメディア", "published": "2026-04-16 14:49", "ym": "2026-04", "category": "", "cat_label": ""}, {"id": 39, "url": "https://www.axismag.jp/posts/2026/04/707426.html", "title": "【米蘭國際家具展2026搶先預覽】TAKT PROJECT Lesson in Relations : Dialogue with Trees #100 | AXIS Web | 以設計觀點傳達人類可能性與創造性的媒體", "orig_title": "【ミラノサローネ2026プレビュー】TAKT PROJECT Lesson in Relations : Dialogue with Trees #100 | AXIS Web | デザインの視点で、人間の可能性や創造性を伝えるメディア", "published": "2026-04-16 12:37", "ym": "2026-04", "category": "", "cat_label": ""}, {"id": 40, "url": "https://www.axismag.jp/posts/2026/04/707311.html", "title": "nendo重新定義Peach的品牌體驗 | AXIS Web | 以設計觀點傳達人類可能性與創造性的媒體", "orig_title": "nendoが再定義するPeachのブランド体験 | AXIS Web | デザインの視点で、人間の可能性や創造性を伝えるメディア", "published": "2026-04-15 14:17", "ym": "2026-04", "category": "business", "cat_label": "商業 Business"}, {"id": 41, "url": "https://www.axismag.jp/posts/2026/04/706680.html", "title": "【米蘭家具展2026搶先看】Poetic Curiosity＋三菱化學 Curious Matters | AXIS Web | 以設計的觀點，傳遞人類的可能性與創造力之媒體", "orig_title": "【ミラノサローネ2026プレビュー】ポエティック・キュリオシティ＋三菱ケミカル Curious Matters（キュリアス・マター） | AXIS Web | デザインの視点で、人間の可能性や創造性を伝えるメディア", "published": "2026-04-15 10:07", "ym": "2026-04", "category": "", "cat_label": ""}, {"id": 42, "url": "https://www.axismag.jp/posts/2026/04/706501.html", "title": "【米蘭家具展2026搶先預覽】小泉 創 瀝青家具系列「As」 | AXIS Web | 以設計的觀點，傳遞人類可能性與創造性的媒體", "orig_title": "【ミラノサローネ2026プレビュー】小泉 創 アスファルトの家具コレクション「As」 | AXIS Web | デザインの視点で、人間の可能性や創造性を伝えるメディア", "published": "2026-04-14 13:54", "ym": "2026-04", "category": "", "cat_label": ""}, {"id": 43, "url": "https://www.axismag.jp/posts/2026/04/706486.html", "title": "【米蘭設計週2026預覽】橫田純一郎 Refining the Ordinary（普通／將日常打磨成精緻） | AXIS Web | 以設計觀點傳達人類可能性與創造力的媒體", "orig_title": "【ミラノサローネ2026プレビュー】横田純一郎 Refining the Ordinary（普通／あたりまえを洗練させる） | AXIS Web | デザインの視点で、人間の可能性や創造性を伝えるメディア", "published": "2026-04-14 13:52", "ym": "2026-04", "category": "", "cat_label": ""}, {"id": 44, "url": "https://www.axismag.jp/posts/2026/04/705734.html", "title": "重新編織輕井澤風土的旅宿體驗。「HACIENDA KARUIZAWA」與溫浴設施盛大開幕 | AXIS Web | 以設計觀點傳遞人類可能性與創造力的媒體", "orig_title": "軽井沢の風土を編み直す滞在体験。「HACIENDA KARUIZAWA」と温浴施設が開業 | AXIS Web | デザインの視点で、人間の可能性や創造性を伝えるメディア", "published": "2026-04-14 13:36", "ym": "2026-04", "category": "business", "cat_label": "商業 Business"}, {"id": 45, "url": "https://www.axismag.jp/posts/2026/04/707033.html", "title": "追蹤隈研吾十五年歷程的紀錄片《粒子的舞蹈》現正熱映中 | AXIS Web | 以設計觀點傳達人類可能性與創造力的媒體\n\n\nNow I'm translating the author names and the opening paragraph, working through the key details about the documentary and its subject.\n\nThe film documents Kengo Kuma's architectural practice over 15 years, capturing his work across 16 countries and 80 projects—from post-earthquake reconstruction in Tohoku to the National Stadium and architectural education initiatives. I'm also noting the film's stylistic approach, using fragmented, particle-like imagery to capture moments of societal transformation, and highlighting how it portrays the recovery process in affected regions like Minamisanriku, Rikuzen Takada, and Tome.\n\nThe film serves as a documentary record of Japanese resilience and reconstruction wisdom. Director Hiromoto Oka describes it as an attempt to convey Kuma's sensitivity in connecting the intelligence of past, present, and future, and his ability to create tailored, place-based architecture through the accumulated fragments of his work.\n\nThe Image Forum screenings run through mid-April, and I'm considering catching it this weekend at the theater. The film is directed by Hiromoto Oka, who has spent 15 years following Kengo Kuma's architectural practice across 80 projects in 16 countries, documenting everything from post-earthquake reconstruction efforts to major stadiums and educational initiatives.\n\nThe work uses a pointillist approach through particle-like fragments to explore Kuma's questioning of architectural possibilities during times of social transformation like the Tokyo 2020 Games and the pandemic. It captures both the reconstruction happening in communities across Tohoku and the everyday life of those areas, creating a documentary record of Japan's approach to disaster recovery and the wisdom gained through that process.\n\nDirector Hiromoto Oka describes the film as a 15-year documentary following Kuma's architectural philosophy—connecting the intelligence of past, present, and future—through these fragmented, project-based moments, hoping viewers will absorb his place-based thinking and the insight that emerges from working with communities.\n</think>\n\n===標題===\n追蹤隈研吾十五年歷程的紀錄片《粒子的舞蹈》現正熱映中 | AXIS Web | 以設計觀點傳達人類可能性與創造力的媒體", "orig_title": "隈 研吾の15年を追うドキュメンタリー『粒子のダンス』公開中 | AXIS Web | デザインの視点で、人間の可能性や創造性を伝えるメディア", "published": "2026-04-13 09:06", "ym": "2026-04", "category": "architecture", "cat_label": "建築 Architecture"}, {"id": 46, "url": "https://www.axismag.jp/posts/2026/04/706065.html", "title": "從「被述說的對象」到「述說的主體」。奈洛比巨大貧民窟基貝拉的年輕人所舉辦的攝影・影像展 | AXIS Web | 以設計的觀點，傳遞人類可能性與創造力的媒體", "orig_title": "「語られる側」から「語る側」へ。ナイロビの巨大スラム・キベラの若者による写真・映像展 | AXIS Web | デザインの視点で、人間の可能性や創造性を伝えるメディア", "published": "2026-04-09 16:15", "ym": "2026-04", "category": "social", "cat_label": "社會 Social"}, {"id": 47, "url": "https://www.axismag.jp/posts/2026/04/706581.html", "title": "重新思考光的標準 Panasonic「MODIFY In Lights」盛大開展 | AXIS Web | 以設計觀點傳遞人類可能性與創造性的媒體", "orig_title": "光のスタンダードを再考 パナソニック「MODIFY In Lights」開催 | AXIS Web | デザインの視点で、人間の可能性や創造性を伝えるメディア", "published": "2026-04-08 16:40", "ym": "2026-04", "category": "interior", "cat_label": "室內 Interior"}, {"id": 48, "url": "https://www.axismag.jp/posts/2026/04/705710.html", "title": "以毒為主題的NIFREL新區域「接觸毒物」——從「可怕」到「厲害」", "orig_title": "毒をテーマにしたNIFRELの新ゾーン「どくにふれる」「こわい」から「すごい」へ | AXIS Web | デザインの視点で、人間の可能性や創造性を伝えるメディア", "published": "2026-04-08 16:35", "ym": "2026-04", "category": "science", "cat_label": "科學 Science"}, {"id": 49, "url": "https://www.axismag.jp/posts/2026/04/704495.html", "title": "為分解、移築而設計的木造模組建築「prewood」", "orig_title": "分解・移築を前提とした木造モジュール建築「prewood」 | AXIS Web | デザインの視点で、人間の可能性や創造性を伝えるメディア", "published": "2026-04-08 09:17", "ym": "2026-04", "category": "product", "cat_label": "產品 Product"}, {"id": 50, "url": "https://www.axismag.jp/posts/2026/04/704360.html", "title": "祝祭文化與照明設計的交會點。從「Life-Size」看手工藝的重新詮釋 LZF Lamps | AXIS Web | 以設計觀點傳遞人類可能性與創造性的媒體", "orig_title": "祝祭文化と照明デザインの接点。「Life-Size」に見るクラフトの再解釈 LZF Lamps | AXIS Web | デザインの視点で、人間の可能性や創造性を伝えるメディア", "published": "2026-04-06 16:27", "ym": "2026-04", "category": "craft", "cat_label": "工藝 Craft"}, {"id": 51, "url": "https://www.axismag.jp/posts/2026/04/706317.html", "title": "從紙頁飛向數位。月刊《ぴあ》『とぶ！ぴあ』睽違15年復刊 | AXIS Web | 以設計的視角，傳遞人類可能性與創造性的媒體", "orig_title": "紙の頁からデジタルへ飛ぶ。月刊ぴあ『とぶ！ぴあ』が15年ぶりに復刊 | AXIS Web | デザインの視点で、人間の可能性や創造性を伝えるメディア", "published": "2026-04-06 15:03", "ym": "2026-04", "category": "business", "cat_label": "商業 Business"}, {"id": 52, "url": "https://www.axismag.jp/posts/2026/04/702239.html", "title": "エクシィズ發表以家電廢材為原料、CO²排放量減少55%的回收磁磚「Uool」| AXIS Web | 以設計觀點傳達人類可能性與創造力的媒體", "orig_title": "エクシィズ、家電廃材を原料にCO²排出量55％削減のリサイクルタイル「Uool」を発表 | AXIS Web | デザインの視点で、人間の可能性や創造性を伝えるメディア", "published": "2026-04-03 15:03", "ym": "2026-04", "category": "product", "cat_label": "產品 Product"}, {"id": 53, "url": "https://www.axismag.jp/posts/2026/04/705171.html", "title": "搖撼遊具與雕塑之界線　艾洛·阿爾尼歐搖椅《羅西南特》", "orig_title": "遊具とオブジェの境界を揺さぶる エーロ・アールニオによるロッキングチェア「ロシナンテ」 | AXIS Web | デザインの視点で、人間の可能性や創造性を伝えるメディア", "published": "2026-04-03 09:45", "ym": "2026-04", "category": "business", "cat_label": "商業 Business"}, {"id": 54, "url": "https://www.axismag.jp/posts/2026/04/705514.html", "title": "以體驗型展示間聞名的「Aria & Aura」進軍南青山——「Aria & Aura Aoyama Gallery NATURA MAESTRA」盛大开幕 | AXIS Web | 以設計視角傳達人類潛能與創造力的媒體", "orig_title": "建具の体験型ショールームが南青山に誕生。「Aria & Aura Aoyama Gallery NATURA MAESTRA」 | AXIS Web | デザインの視点で、人間の可能性や創造性を伝えるメディア", "published": "2026-04-02 14:39", "ym": "2026-04", "category": "business", "cat_label": "商業 Business"}, {"id": 55, "url": "https://www.axismag.jp/posts/2026/04/702622.html", "title": "探究原研哉思考起點的原畫展「DRAW——原研哉正在描繪」京都ddd畫廊 | AXIS Web | 以設計觀點傳達人類可能性與創造性的媒體", "orig_title": "原 研哉の思考の起点に迫る原画展 「DRAW―原研哉は描いている」京都dddギャラリー | AXIS Web | デザインの視点で、人間の可能性や創造性を伝えるメディア", "published": "2026-04-02 09:07", "ym": "2026-04", "category": "graphic", "cat_label": "圖像 Graphic"}, {"id": 56, "url": "https://www.axismag.jp/posts/2026/03/704773.html", "title": "伊東豊雄建築設計事務所＋S# Architects 韓國「華城市藝術博物館」設計競賽中榮獲最優秀提案 | AXIS Web | 以設計觀點傳遞人類可能性與創造力的媒體", "orig_title": "伊東豊雄建築設計事務所＋S# Architects 韓国「華城市アートミュージアム」設計競技で最優秀案に | AXIS Web | デザインの視点で、人間の可能性や創造性を伝えるメディア", "published": "2026-03-31 09:43", "ym": "2026-03", "category": "architecture", "cat_label": "建築 Architecture"}, {"id": 57, "url": "https://www.axismag.jp/posts/2026/03/702960.html", "title": "沙烏地阿拉伯利雅德地鐵站——配備地下庭園，斯諾赫塔打造嶄新都市門戶", "orig_title": "サウジアラビア・リヤドに地下庭園を備えた地下鉄駅、スノヘッタが新たな都市の玄関口を設計 | AXIS Web | デザインの視点で、人間の可能性や創造性を伝えるメディア", "published": "2026-03-30 18:48", "ym": "2026-03", "category": "architecture", "cat_label": "建築 Architecture"}, {"id": 58, "url": "https://www.axismag.jp/posts/2026/03/705426.html", "title": "協作創造的飲食文化──持續進化的丹麥日常飲食 | AXIS Web | 以設計視角傳遞人類可能性與創造性的媒體", "orig_title": "協働がつくる食文化 ──進化し続けるデンマークの日常食 | AXIS Web | デザインの視点で、人間の可能性や創造性を伝えるメディア", "published": "2026-03-30 14:35", "ym": "2026-03", "category": "food", "cat_label": "食物 Food"}, {"id": 59, "url": "https://www.axismag.jp/posts/2026/03/703868.html", "title": "特別展覽「加守田章二與IM MEN」於京都國立現代美術館舉辦", "orig_title": "特別展示「加守田章二とIM MEN」 京都国立近代美術館で開催 | AXIS Web | デザインの視点で、人間の可能性や創造性を伝えるメディア", "published": "2026-03-30 14:08", "ym": "2026-03", "category": "fashion", "cat_label": "時尚 Fashion"}, {"id": 60, "url": "https://www.axismag.jp/posts/2026/03/704056.html", "title": "選擇「穿戴」作業支援——義大利Comau公司推出穿戴式機器人新產品「MATE-XT GO」 | AXIS Web | 以設計視角傳遞人類可能性與創造力的媒體", "orig_title": "作業支援を“着る”という選択。Comau社のウェラブルロボティクスの新製品「MATE-XT GO」 | AXIS Web | デザインの視点で、人間の可能性や創造性を伝えるメディア", "published": "2026-03-27 15:49", "ym": "2026-03", "category": "technology", "cat_label": "科技 Technology"}, {"id": 61, "url": "https://www.axismag.jp/posts/2026/03/702687.html", "title": "ヘザウィック工作室提出新地標提案 鹿特丹公共設施計畫「都市綠洲」", "orig_title": "ヘザウィック・スタジオが新たなランドマークを提案 ロッテルダムの公共施設計画「アーバンリーフ」 | AXIS Web | デザインの視点で、人間の可能性や創造性を伝えるメディア", "published": "2026-03-25 14:29", "ym": "2026-03", "category": "culture", "cat_label": "文化 Culture"}, {"id": 62, "url": "https://www.axismag.jp/posts/2026/03/704343.html", "title": "BALMUDA打造「感受時間」的時鐘──體驗雨聲與光的「The Clock」", "orig_title": "バルミューダから“時間を感じる”ための時計。雨音や光を体験する「The Clock」 | AXIS Web | デザインの視点で、人間の可能性や創造性を伝えるメディア", "published": "2026-03-24 14:01", "ym": "2026-03", "category": "product", "cat_label": "產品 Product"}, {"id": 63, "url": "https://www.axismag.jp/posts/2026/03/703995.html", "title": "INVADER睽違16年在日本舉辦個展 伊勢丹新宿店「Hyperspace」展覽正式啟幕 | AXIS Web｜以設計視角傳遞人類可能性與創造力的媒體", "orig_title": "INVADER、日本で16年ぶりの個展を開催 伊勢丹新宿店で「Hyperspace」展がスタート | AXIS Web | デザインの視点で、人間の可能性や創造性を伝えるメディア", "published": "2026-03-23 17:33", "ym": "2026-03", "category": "product", "cat_label": "產品 Product"}, {"id": 64, "url": "https://www.axismag.jp/posts/2026/03/702271.html", "title": "カリモク RESEARCH 與 Devon Turnbull 協作。探索聲音與「間」的『Survey 03』", "orig_title": "カリモク リサーチがDevon Turnbull（デヴィン・ターンブル）と協働 。音と「間」を探る『Survey 03』 | AXIS Web | デザインの視点で、人間の可能性や創造性を伝えるメディア", "published": "2026-03-23 13:08", "ym": "2026-03", "category": "product", "cat_label": "產品 Product"}, {"id": 65, "url": "https://www.axismag.jp/posts/2026/03/704221.html", "title": "將打孔金屬板的視覺效果立體化。EETAL × monoya「Punching Block」展覽，於東京、京都舉辦 | AXIS Web | 從設計觀點出發，傳遞人類可能性與創造力的媒體", "orig_title": "パンチングメタルの見え方を立体化。EETAL × monoyaによる「Punching Block」展、東京・京都で開催 | AXIS Web | デザインの視点で、人間の可能性や創造性を伝えるメディア", "published": "2026-03-19 10:12", "ym": "2026-03", "category": "product", "cat_label": "產品 Product"}, {"id": 66, "url": "https://www.axismag.jp/posts/2026/03/703752.html", "title": "舊橫濱市府廳將於3月19日化身為「BASEGATE橫濱關內」。以新舊融合為軸，打造連接城市記憶與未來的據點 | AXIS Web | 以設計視角傳達人類可能性與創造力的媒體", "orig_title": "旧横浜市庁舎が3月19日「BASEGATE横浜関内」に。新旧融合を軸に、都市の記憶と未来をつなぐ拠点へ | AXIS Web | デザインの視点で、人間の可能性や創造性を伝えるメディア", "published": "2026-03-19 09:28", "ym": "2026-03", "category": "architecture", "cat_label": "建築 Architecture"}, {"id": 67, "url": "https://www.axismag.jp/posts/2026/03/703882.html", "title": "尼克・本特爾重構購物推車，將其轉化為象徵消費生活的包款「The Trolley Bag」", "orig_title": "ニック・ベンテルがショッピングカートを再構築。消費生活を象徴するバッグへと転換した「The Trolley Bag」 | AXIS Web | デザインの視点で、人間の可能性や創造性を伝えるメディア", "published": "2026-03-18 13:28", "ym": "2026-03", "category": "product", "cat_label": "產品 Product"}, {"id": 68, "url": "https://www.axismag.jp/posts/2026/03/703578.html", "title": "從山望向天空的攝影師・林雅之 個展「空觀山步」、於Gallery5610展出約50幅黑白攝影作品 | AXIS Web | 以設計的觀點，傳達人類的可能性與創造性的媒體", "orig_title": "山から空を見つめる写真家・林雅之の個展「空観山歩」、 Gallery5610でモノクロ写真約50点を展示 | AXIS Web | デザインの視点で、人間の可能性や創造性を伝えるメディア", "published": "2026-03-17 15:47", "ym": "2026-03", "category": "", "cat_label": ""}, {"id": 69, "url": "https://www.axismag.jp/posts/2026/03/702284.html", "title": "小米與徠卡，發表追求拍攝性能的兩款智慧型手機 | AXIS Web | 以設計觀點傳遞人類可能性與創造力的媒體", "orig_title": "シャオミとライカ、撮影性能を追求した2機種のスマートフォンを発売 | AXIS Web | デザインの視点で、人間の可能性や創造性を伝えるメディア", "published": "2026-03-16 18:17", "ym": "2026-03", "category": "product", "cat_label": "產品 Product"}, {"id": 70, "url": "https://www.axismag.jp/posts/2026/03/702942.html", "title": "香港故宮文化博物館運行古代埃及展主題巴士，將展覽世界觀延伸至街頭", "orig_title": "香港故宮文化博物館、 古代エジプト展の世界観を街へ広げるテーマバスを運行 | AXIS Web | デザインの視点で、人間の可能性や創造性を伝えるメディア", "published": "2026-03-13 15:30", "ym": "2026-03", "category": "", "cat_label": ""}, {"id": 71, "url": "https://www.axismag.jp/posts/2026/03/702672.html", "title": "英國設計師 Jasper Morrison 操刀戶外系列「OUTDOOR MARKET BY JASPER MORRISON FOR HAY」正式登場 | AXIS Web | 以設計觀點傳遞人類可能性與創造力的媒體", "orig_title": "ジャスパー・モリソンが手がけるアウトドアコレクション 「OUTDOOR MARKET BY JASPER MORRISON FOR HAY」が登場 | AXIS Web | デザインの視点で、人間の可能性や創造性を伝えるメディア", "published": "2026-03-13 14:53", "ym": "2026-03", "category": "interior", "cat_label": "室內 Interior"}, {"id": 72, "url": "https://www.axismag.jp/posts/2026/03/702746.html", "title": "隈研吾設計的「卡佩拉京都」 公開體現現代町家的設計概念", "orig_title": "隈 研吾設計の「カペラ京都」 現代の町家を体現するデザインコンセプトを公開 | AXIS Web | デザインの視点で、人間の可能性や創造性を伝えるメディア", "published": "2026-03-12 17:01", "ym": "2026-03", "category": "architecture", "cat_label": "建築 Architecture"}, {"id": 73, "url": "https://www.axismag.jp/posts/2026/03/702733.html", "title": "獨立時計師康斯坦丁·查金×BEHRENS的合作 「Ace of Heart」最終章發布 | AXIS Web | 以設計觀點傳達人類可能性與創造力的媒體", "orig_title": "独立時計師コンスタンチン・チャイキン×BEHRENSのコラボ 「Ace of Heart」最終章がリリース | AXIS Web | デザインの視点で、人間の可能性や創造性を伝えるメディア", "published": "2026-03-12 16:22", "ym": "2026-03", "category": "product", "cat_label": "產品 Product"}, {"id": 74, "url": "https://www.axismag.jp/posts/2026/03/702254.html", "title": "靜岡家具與木工技術展覽會「FASS」第一屆舉辦，西田悠真等人擔任策劃與空間規劃 | AXIS Web | 以設計觀點傳達人類可能性與創造性的媒體", "orig_title": "静岡の家具と木工技術の展示会「FASS」第1回開催、西田悠真ら有志が企画・空間計画を担当 | AXIS Web | デザインの視点で、人間の可能性や創造性を伝えるメディア", "published": "2026-03-12 10:03", "ym": "2026-03", "category": "interior", "cat_label": "室內 Interior"}, {"id": 75, "url": "https://www.axismag.jp/posts/2026/03/702635.html", "title": "布朗名作音響約60件展示販售 「BRAUN AUDIO DESIGN」展覽於山梨舉辦 | AXIS Web | 以設計視角傳遞人類可能性與創造性的媒體", "orig_title": "ブラウンの名作オーディオ約60点を展示販売 「BRAUN AUDIO DESIGN」展が山梨で開催 | AXIS Web | デザインの視点で、人間の可能性や創造性を伝えるメディア", "published": "2026-03-10 15:03", "ym": "2026-03", "category": "product", "cat_label": "產品 Product"}, {"id": 76, "url": "https://www.axismag.jp/posts/2026/03/701782.html", "title": "美術家・藤原大的個展「人之中才有的自然」 在印度進行色彩狩獵的成果於螺旋花園發表 | AXIS Web | 以設計的觀點，傳達人類的可能性與創造力的媒體", "orig_title": "美術家・藤原大の個展「人の中にしかない自然」 インドでのカラーハンティング成果をスパイラルガーデンで発表 | AXIS Web | デザインの視点で、人間の可能性や創造性を伝えるメディア", "published": "2026-03-10 14:47", "ym": "2026-03", "category": "fashion", "cat_label": "時尚 Fashion"}, {"id": 77, "url": "https://www.axismag.jp/posts/2026/03/702527.html", "title": "podcast 節目「設計之前」首次公開錄音 與次世代設計師真人對談的2週年活動開催！", "orig_title": "ポッドキャスト「デザインの手前」初の公開収録 次世代デザイナーとリアルに語る2周年イベントを開催！ | AXIS Web | デザインの視点で、人間の可能性や創造性を伝えるメディア", "published": "2026-03-06 13:43", "ym": "2026-03", "category": "", "cat_label": ""}, {"id": 78, "url": "https://www.axismag.jp/posts/2026/03/701838.html", "title": "由史諾赫塔規劃設計的上海大劇院，預定2026年下半年開幕", "orig_title": "スノヘッタ設計の上海グランドオペラハウス、2026年後半開館へ | AXIS Web | デザインの視点で、人間の可能性や創造性を伝えるメディア", "published": "2026-03-06 10:28", "ym": "2026-03", "category": "architecture", "cat_label": "建築 Architecture"}, {"id": 79, "url": "https://www.axismag.jp/posts/2026/03/701422.html", "title": "Bang & Olufsen創立100週年紀念展「Beautiful Sound and Design」舉辦 | AXIS Web | 以設計觀點傳遞人類可能性與創造性的媒體", "orig_title": "Bang & Olufsen創立100周年記念展「Beautiful Sound and Design」開催 | AXIS Web | デザインの視点で、人間の可能性や創造性を伝えるメディア", "published": "2026-03-05 13:17", "ym": "2026-03", "category": "product", "cat_label": "產品 Product"}, {"id": 80, "url": "https://www.axismag.jp/posts/2026/03/701852.html", "title": "EETAL邁向第5年的策劃展「PAST AND FUTURE」提出精密板金嶄新可能性", "orig_title": "EETALの5年を辿る企画展「PAST AND FUTURE」 精密板金の新たな可能性を提示 | AXIS Web | デザインの視点で、人間の可能性や創造性を伝えるメディア", "published": "2026-03-04 19:55", "ym": "2026-03", "category": "product", "cat_label": "產品 Product"}, {"id": 81, "url": "https://www.axismag.jp/posts/2026/03/700312.html", "title": "光滿溢的照明——設計師田村奈穂與WonderGlass協力發表新作「FLUID」 | AXIS Web | 以設計的觀點，傳達人類的可能性與創造力", "orig_title": "光を湛える照明 田村奈穂、WonderGlassと協働した新作「FLUID」を発表 | AXIS Web | デザインの視点で、人間の可能性や創造性を伝えるメディア", "published": "2026-03-04 13:12", "ym": "2026-03", "category": "product", "cat_label": "產品 Product"}, {"id": 82, "url": "https://www.axismag.jp/posts/2026/03/702317.html", "title": "平面設計師 永井一正先生辭世 在戰後日本視覺文化上刻下的足跡", "orig_title": "グラフィックデザイナー 永井一正氏逝去 戦後日本の視覚文化に刻んだ足跡 | AXIS Web | デザインの視点で、人間の可能性や創造性を伝えるメディア", "published": "2026-03-03 18:33", "ym": "2026-03", "category": "graphic", "cat_label": "圖像 Graphic"}, {"id": 83, "url": "https://www.axismag.jp/posts/2026/03/700928.html", "title": "從建築板金的「裁切」「折彎」誕生的極簡鏡 Fulcrum「Trim Mirror」上市 | AXIS Web | 以設計觀點傳達人類可能性與創造性的媒體", "orig_title": "建築板金の「切る」「折る」から生まれるミニマルな鏡 Fulcrum「Trim Mirror」発売 | AXIS Web | デザインの視点で、人間の可能性や創造性を伝えるメディア", "published": "2026-02-27 18:34", "ym": "2026-02", "category": "product", "cat_label": "產品 Product"}, {"id": 84, "url": "https://www.axismag.jp/posts/2026/02/701454.html", "title": "Kokuyo Design Award 2026「NEW GENERATION獎」10件獲獎作品出爐 | AXIS Web | 以設計觀點傳達人類可能性與創造力的媒體", "orig_title": "コクヨデザインアワード2026 「NEW GENERATION賞」受賞10作品が決定 | AXIS Web | デザインの視点で、人間の可能性や創造性を伝えるメディア", "published": "2026-02-27 16:32", "ym": "2026-02", "category": "product", "cat_label": "產品 Product"}, {"id": 85, "url": "https://www.axismag.jp/posts/2026/02/701683.html", "title": "單身者專屬共居租賃住宅「HAUN大崎」，於五反田・大崎地區盛大開幕", "orig_title": "単身者向けコリビング賃貸「HAUN大崎」、五反田・大崎エリアに開業 | AXIS Web | デザインの視点で、人間の可能性や創造性を伝えるメディア", "published": "2026-02-27 15:20", "ym": "2026-02", "category": "business", "cat_label": "商業 Business"}, {"id": 86, "url": "https://www.axismag.jp/posts/2026/02/700838.html", "title": "「或ると在る的研究展」於FabCafe Kyoto登場 以設計探尋工具與人的當代關係 | AXIS Web | 以設計觀點傳達人類可能性與創造力的媒體", "orig_title": "「或ると在るの研究展」FabCafe Kyotoで開催 道具と人の関係性を探るデザインの現在 | AXIS Web | デザインの視点で、人間の可能性や創造性を伝えるメディア", "published": "2026-02-26 14:55", "ym": "2026-02", "category": "product", "cat_label": "產品 Product"}, {"id": 87, "url": "https://www.axismag.jp/posts/2026/02/700968.html", "title": "2026年平面設計獎揭曉 田部井美奈《光與圖形及其周邊》榮獲龜倉雄策獎與JAGDA獎雙料殊榮 | AXIS Web | 以設計觀點傳達人類可能性與創造性的媒體", "orig_title": "2026年のグラフィックデザイン賞が決定 田部井美奈の「光と図形と、その周辺」が亀倉雄策賞・JAGDA賞二重受賞 | AXIS Web | デザインの視点で、人間の可能性や創造性を伝えるメディア", "published": "2026-02-25 18:24", "ym": "2026-02", "category": "graphic", "cat_label": "圖像 Graphic"}, {"id": 88, "url": "https://www.axismag.jp/posts/2026/02/701107.html", "title": "Global Creators Labs | 放大人類「創造」力量的玩具 LEGO Design | AXIS Web | 以設計視角傳達人類可能性與創造性的媒體", "orig_title": "Global Creators Labs | 人の「つくる」力を増幅させる玩具 LEGO Design | AXIS Web | デザインの視点で、人間の可能性や創造性を伝えるメディア", "published": "2026-02-25 09:05", "ym": "2026-02", "category": "", "cat_label": ""}, {"id": 89, "url": "https://www.axismag.jp/posts/2026/02/701093.html", "title": "從一塊拼圖說起｜野見山 櫻 #7 Cherry（1946）瑪麗・古多美・雷托", "orig_title": "ひとつのピースから｜野見山 桜 #7 Cherry（1946）マリー・グドメ・レト | AXIS Web | デザインの視点で、人間の可能性や創造性を伝えるメディア", "published": "2026-02-24 17:18", "ym": "2026-02", "category": "", "cat_label": ""}, {"id": 90, "url": "https://www.axismag.jp/posts/2026/02/701074.html", "title": "一切的開端｜三澤 遙 #7 孔洞與重疊 | AXIS Web | 以設計的視角，傳遞人類的可能性與創造力的媒體", "orig_title": "はじまりのはじまり｜三澤 遥 #7 穴と 重なりと | AXIS Web | デザインの視点で、人間の可能性や創造性を伝えるメディア", "published": "2026-02-24 17:12", "ym": "2026-02", "category": "", "cat_label": ""}, {"id": 91, "url": "https://www.axismag.jp/posts/2026/02/700593.html", "title": "以「造物的記憶」為素材 船場×Yamaha發動機，共創使用機車零件的家具 | AXIS Web | 以設計觀點傳達人類可能性與創造性的媒體", "orig_title": "「モノづくりの記憶」を素材に 船場×ヤマハ発動機、バイク部品を用いたファニチャーを共創 | AXIS Web | デザインの視点で、人間の可能性や創造性を伝えるメディア", "published": "2026-02-24 14:13", "ym": "2026-02", "category": "product", "cat_label": "產品 Product"}, {"id": 92, "url": "https://www.axismag.jp/posts/2026/02/700853.html", "title": "真鍋大度和Sinan Bokesoy開發，以自然語言即時生成照明燈光設計的「SPOTLIGHT AI」 | AXIS Web | 以設計觀點傳遞人類可能性與創造力的媒體", "orig_title": "真鍋大度とSinan Bokesoyが開発、自然言語で照明演出をリアルタイム生成する「SPOTLIGHT AI」 | AXIS Web | デザインの視点で、人間の可能性や創造性を伝えるメディア", "published": "2026-02-24 14:04", "ym": "2026-02", "category": "technology", "cat_label": "科技 Technology"}, {"id": 93, "url": "https://www.axismag.jp/posts/2026/02/700633.html", "title": "以香氣記錄白馬之森「HAKUBA GIN」上市 寄寓自然保育訊息的精釀琴酒", "orig_title": "白馬の森を香りで記録する「HAKUBA GIN」発売 自然保全へのメッセージを込めたクラフトジン | AXIS Web | デザインの視点で、人間の可能性や創造性を伝えるメディア", "published": "2026-02-20 16:50", "ym": "2026-02", "category": "product", "cat_label": "產品 Product"}, {"id": 94, "url": "https://www.axismag.jp/posts/2026/02/700328.html", "title": "完成度70%的家具提案 センプレデザインの全新品牌「SOSEI PROJECT.」| AXIS Web | 以設計觀點傳遞人類可能性與創造性的媒體", "orig_title": "完成度70％の家具という提案 センプレデザインの新ブランド「SOSEI PROJECT.」 | AXIS Web | デザインの視点で、人間の可能性や創造性を伝えるメディア", "published": "2026-02-20 15:57", "ym": "2026-02", "category": "product", "cat_label": "產品 Product"}, {"id": 95, "url": "https://www.axismag.jp/posts/2026/02/700128.html", "title": "提取金屬的「氣息」與「質感」 壁畫品牌WhO發表深地宏昌設計新花色44款 | AXIS Web | 以設計觀點傳達人類可能性與創造性的媒體", "orig_title": "金属の「気配」と「質感」を抽出 壁紙ブランドWhO、深地宏昌がデザインした新柄44点を発表 | AXIS Web | デザインの視点で、人間の可能性や創造性を伝えるメディア", "published": "2026-02-20 12:56", "ym": "2026-02", "category": "product", "cat_label": "產品 Product"}, {"id": 96, "url": "https://www.axismag.jp/posts/2026/02/699586.html", "title": "重新審視庵治石與祈禱 高橋石材的物件系列「Repose」 | AXIS Web | 以設計的觀點，傳達人類的可能性與創造力的媒體", "orig_title": "庵治石と祈りを見つめ直す 髙橋石材のオブジェクトライン「Repose」 | AXIS Web | デザインの視点で、人間の可能性や創造性を伝えるメディア", "published": "2026-02-19 14:34", "ym": "2026-02", "category": "product", "cat_label": "產品 Product"}, {"id": 97, "url": "https://www.axismag.jp/posts/2026/02/700200.html", "title": "活用高精度抜き型技術 高橋型精的產品品牌「KIRIORI」 | AXIS Web | 以設計視角傳遞人類的可能性與創造力之媒體", "orig_title": "高精度抜き型技術を生かす 高橋型精のプロダクトブランド「KIRIORI」 | AXIS Web | デザインの視点で、人間の可能性や創造性を伝えるメディア", "published": "2026-02-19 14:14", "ym": "2026-02", "category": "product", "cat_label": "產品 Product"}, {"id": 98, "url": "https://www.axismag.jp/posts/2026/02/699239.html", "title": "松屋銀座「設計藝廊1953」首度公開徵選展覽企劃 日本設計委員會舉辦「DESIGN GALLERY AWARD」| AXIS Web | 以設計視角傳達人類可能性與創造力的媒體", "orig_title": "松屋銀座「デザインギャラリー1953」で初の展覧会企画公募 日本デザインコミッティーが「DESIGN GALLERY AWARD」を開催 | AXIS Web | デザインの視点で、人間の可能性や創造性を伝えるメディア", "published": "2026-02-19 14:09", "ym": "2026-02", "category": "", "cat_label": ""}, {"id": 99, "url": "https://www.axismag.jp/posts/2026/02/700046.html", "title": "H&M設計大獎睽違5年重新啟動 以歷年最大規模舉辦 | AXIS Web | 以設計觀點傳遞人類可能性與創造力的媒體", "orig_title": "H&Mデザインアワード、5年ぶりに再始動 過去最大規模で開催 | AXIS Web | デザインの視点で、人間の可能性や創造性を伝えるメディア", "published": "2026-02-17 14:26", "ym": "2026-02", "category": "fashion", "cat_label": "時尚 Fashion"}, {"id": 100, "url": "https://www.axismag.jp/posts/2026/02/699857.html", "title": "Synflux參與住友金屬礦山新素材服飾「HOPE WEAR」——近紅外線吸收素材與AI設計融合的原型公開", "orig_title": "Synfluxが住友金属鉱山の新素材ウェア「HOPE WEAR」に参画 近赤外線吸収素材とAI設計を融合したプロトタイプ公開 | AXIS Web | デザインの視点で、人間の可能性や創造性を伝えるメディア", "published": "2026-02-17 13:42", "ym": "2026-02", "category": "technology", "cat_label": "科技 Technology"}, {"id": 101, "url": "https://www.axismag.jp/posts/2026/02/699552.html", "title": "設計師柴山修平與小貫金網製作所 以金網加工技術打造的家具系列「GRILL」 | AXIS Web | 以設計視角傳遞人類可能性與創造力的媒體", "orig_title": "デザイナーの柴山修平と小貫金網製作所による 金網加工技術を生かした家具シリーズ「GRILL」 | AXIS Web | デザインの視点で、人間の可能性や創造性を伝えるメディア", "published": "2026-02-17 13:38", "ym": "2026-02", "category": "product", "cat_label": "產品 Product"}, {"id": 102, "url": "https://www.axismag.jp/posts/2026/02/699541.html", "title": "ELECOM、創業40週年翻新「EGG MOUSE」 採用可替換式保護套的新款預計夏季發售 | AXIS Web | 以設計的觀點，傳達人類的可能性與創造力的媒體", "orig_title": "エレコム、創業40周年で「EGG MOUSE」刷新 着せ替えカバー採用の新モデルを夏に発売予定 | AXIS Web | デザインの視点で、人間の可能性や創造性を伝えるメディア", "published": "2026-02-17 12:40", "ym": "2026-02", "category": "product", "cat_label": "產品 Product"}, {"id": 103, "url": "https://www.axismag.jp/posts/2026/02/699843.html", "title": "重新審視木與人關係的展覽會——狩野佑真與太田翔於Karimoku Commons Tokyo展出中", "orig_title": "木と人の関係を問い直す展覧会 狩野佑真と太田 翔がKarimoku Commons Tokyoで開催中 | AXIS Web | デザインの視点で、人間の可能性や創造性を伝えるメディア", "published": "2026-02-17 08:33", "ym": "2026-02", "category": "product", "cat_label": "產品 Product"}, {"id": 104, "url": "https://www.axismag.jp/posts/2026/02/699567.html", "title": "日本創立的性能跑步品牌HYBEX　品牌首款作品「HX LENS」上市 | AXIS Web | 以設計觀點傳達人類可能性與創造性的媒體", "orig_title": "日本発パフォーマンスランニングブランドHYBEX ブランド初作となる「HX LENS」発売 | AXIS Web | デザインの視点で、人間の可能性や創造性を伝えるメディア", "published": "2026-02-16 16:01", "ym": "2026-02", "category": "product", "cat_label": "產品 Product"}, {"id": 105, "url": "https://www.axismag.jp/posts/2026/02/698888.html", "title": "東京TDC獎2026結果揭曉 從3,605件作品中選出11件獲獎作品 | AXIS Web | 以設計視角傳達人類可能性與創造性的媒體", "orig_title": "東京TDC賞2026結果発表 3,605作品から受賞作11点を選出 | AXIS Web | デザインの視点で、人間の可能性や創造性を伝えるメディア", "published": "2026-02-13 12:38", "ym": "2026-02", "category": "graphic", "cat_label": "圖像 Graphic"}, {"id": 106, "url": "https://www.axismag.jp/posts/2026/02/699261.html", "title": "由汽車部品廢材製成的紙製垃圾桶 Sekineseal工業推出「KAMIKA BIN」| AXIS Web | 以設計觀點傳遞人類可能性與創造力的媒體", "orig_title": "自動車部品材の廃材から生まれた紙のゴミ箱 セキネシール工業が「KAMIKA BIN」を発売 | AXIS Web | デザインの視点で、人間の可能性や創造性を伝えるメディア", "published": "2026-02-11 20:07", "ym": "2026-02", "category": "product", "cat_label": "產品 Product"}, {"id": 107, "url": "https://www.axismag.jp/posts/2026/02/698434.html", "title": "將菊竹清訓的舊駿河銀行進行翻新 緊接著富士吉田的住宿設施「SARUYA KIKU」", "orig_title": "菊竹清訓の旧駿河銀行をリノベーション 富士吉田の宿泊施設「SARUYA KIKU」に続いて | AXIS Web | デザインの視点で、人間の可能性や創造性を伝えるメディア", "published": "2026-02-10 17:24", "ym": "2026-02", "category": "architecture", "cat_label": "建築 Architecture"}, {"id": 108, "url": "https://www.axismag.jp/posts/2026/02/698871.html", "title": "引進可變式傢俱「Sumu Wall」 實驗型飯店「Sumu Ueno East」於東上野盛大開幕", "orig_title": "可変式什器「Sumu Wall」を導入 実験型ホテル「Sumu Ueno East」東上野にオープン | AXIS Web | デザインの視点で、人間の可能性や創造性を伝えるメディア", "published": "2026-02-10 12:19", "ym": "2026-02", "category": "business", "cat_label": "商業 Business"}, {"id": 109, "url": "https://www.axismag.jp/posts/2026/02/699116.html", "title": "Kontrapunkt推出類型鑄造廠「Kontrapunkt Type」 3款字體家族同步亮相 | AXIS Web | 以設計視角傳遞人類可能性與創造力的媒體", "orig_title": "Kontrapunktがタイプファウンドリー「Kontrapunkt Type」をローンチ 3書体ファミリーを提供 | AXIS Web | デザインの視点で、人間の可能性や創造性を伝えるメディア", "published": "2026-02-10 12:13", "ym": "2026-02", "category": "graphic", "cat_label": "圖像 Graphic"}, {"id": 110, "url": "https://www.axismag.jp/posts/2026/02/699096.html", "title": "以鹿糞為素材開發人造石 國廣產業啟動「DEER DROP STONE PROJECT」 | AXIS Web | 以設計觀點傳達人類的可能性與創造力之媒體", "orig_title": "鹿糞を素材に人造石を開発 国広産業が「DEER DROP STONE PROJECT」始動 | AXIS Web | デザインの視点で、人間の可能性や創造性を伝えるメディア", "published": "2026-02-09 17:21", "ym": "2026-02", "category": "product", "cat_label": "產品 Product"}, {"id": 111, "url": "https://www.axismag.jp/posts/2026/02/698720.html", "title": "唐納·賈德 家具與美術同步展示 伊勢丹新宿店舉辦「Donald Judd：Design」展 | AXIS Web | 以設計視角傳遞人類可能性與創造力的媒體", "orig_title": "ドナルド・ジャッド 家具と美術を同時展示 伊勢丹新宿店で「Donald Judd：Design」開催 | AXIS Web | デザインの視点で、人間の可能性や創造性を伝えるメディア", "published": "2026-02-09 14:34", "ym": "2026-02", "category": "product", "cat_label": "產品 Product"}, {"id": 112, "url": "https://www.axismag.jp/posts/2026/02/699027.html", "title": "撼動城市與人心的設計活動", "orig_title": "街と人を動かすデザインイベント | AXIS Web | デザインの視点で、人間の可能性や創造性を伝えるメディア", "published": "2026-02-06 17:11", "ym": "2026-02", "category": "interior", "cat_label": "室內 Interior"}, {"id": 113, "url": "https://www.axismag.jp/posts/2026/02/698986.html", "title": "Kasper Kyster 不設限制，隨心所欲地持續實驗 | AXIS Web | 以設計觀點傳達人類可能性與創造力的媒體", "orig_title": "Kasper Kyster 制約を設けず、思うままに実験しつづける | AXIS Web | デザインの視点で、人間の可能性や創造性を伝えるメディア", "published": "2026-02-06 17:09", "ym": "2026-02", "category": "interior", "cat_label": "室內 Interior"}, {"id": 114, "url": "https://www.axismag.jp/posts/2026/02/699012.html", "title": "Archival Studies 「這真的是最好的做法嗎」——持續叩問建築的可能性 | AXIS Web | 以設計的觀點，傳遞人類的潛能與創造力", "orig_title": "Archival Studies 「本当にこれが最善なのか」、建築のあり方を問い続ける | AXIS Web | デザインの視点で、人間の可能性や創造性を伝えるメディア", "published": "2026-02-06 16:46", "ym": "2026-02", "category": "product", "cat_label": "產品 Product"}, {"id": 115, "url": "https://www.axismag.jp/posts/2026/02/698754.html", "title": "以「新的裝置」為題的設計競賽 Q1設計競賽2025，與美吉工業共同舉辦 | AXIS Web | 以設計觀點傳達人類的可能性與創造力之媒體", "orig_title": "「新しい装置」を問うデザインコンペ Q1デザインコンペティション2025、みよし工業と協働で開催 | AXIS Web | デザインの視点で、人間の可能性や創造性を伝えるメディア", "published": "2026-02-06 14:58", "ym": "2026-02", "category": "", "cat_label": ""}, {"id": 116, "url": "https://www.axismag.jp/posts/2026/01/696520.html", "title": "COVER STORY ビャルケ・インゲルス（建築家）| AXIS Web | 從設計觀點傳達人類可能性與創造性的媒體", "orig_title": "COVER STORY ビャルケ・インゲルス（建築家） | AXIS Web | デザインの視点で、人間の可能性や創造性を伝えるメディア", "published": "2026-02-06 14:30", "ym": "2026-02", "category": "art", "cat_label": "藝術 Art"}, {"id": 117, "url": "https://www.axismag.jp/posts/2026/02/698421.html", "title": "一體式車褲設計將空氣阻力降至最低 Aerobag發表專業自行車競技用穿戴式安全氣囊", "orig_title": "ビブショーツ一体型で空気抵抗を最小化 Aerobagがプロサイクリング向けウェアラブルエアバッグを発表 | AXIS Web | デザインの視点で、人間の可能性や創造性を伝えるメディア", "published": "2026-02-06 10:58", "ym": "2026-02", "category": "product", "cat_label": "產品 Product"}, {"id": 118, "url": "https://www.axismag.jp/posts/2025/11/680037.html", "title": "追溯巨匠們的思想 策劃展「設計的老師」將於21_21 DESIGN SIGHT舉辦 | AXIS Web | 以設計觀點傳遞人類可能性與創造性的媒體", "orig_title": "巨匠たちの思想をたどる 企画展「デザインの先生」が21_21 DESIGN SIGHTで開催 | AXIS Web | デザインの視点で、人間の可能性や創造性を伝えるメディア", "published": "2026-02-05 13:58", "ym": "2026-02", "category": "", "cat_label": ""}, {"id": 119, "url": "https://www.axismag.jp/posts/2026/02/698765.html", "title": "馬汀・馬吉拉舉辦日本首場大型個展 感性源流於歷史邸宅中升起 | AXIS Web | 以設計觀點傳遞人類可能性與創造性的媒體", "orig_title": "マルタン・マルジェラ、日本初の大規模個展を開催 歴史的邸宅で立ち上がる、感性の源流 | AXIS Web | デザインの視点で、人間の可能性や創造性を伝えるメディア", "published": "2026-02-05 01:03", "ym": "2026-02", "category": "art", "cat_label": "藝術 Art"}, {"id": 120, "url": "https://www.axismag.jp/posts/2026/02/698291.html", "title": "瓦爾納·潘頓逝世100週年紀念 維特拉「愛心錐形椅」限定款發表 | AXIS Web | 以設計觀點傳達人類可能性與創造性的媒體", "orig_title": "ヴァーナー・パントン生誕100周年記念 ヴィトラ「ハート コーン チェア」限定モデル発表 | AXIS Web | デザインの視点で、人間の可能性や創造性を伝えるメディア", "published": "2026-02-04 17:51", "ym": "2026-02", "category": "product", "cat_label": "產品 Product"}, {"id": 121, "url": "https://www.axismag.jp/posts/2026/02/698277.html", "title": "邁向將吸音「整合」進去的思維——Pixii Dust Technologies發表新型吸音模組「iwawemi OC-β」 | AXIS Web | 以設計觀點傳達人類可能性與創造性的媒體", "orig_title": "吸音を「組込む」発想へ ピクシーダストテクノロジーズが新吸音モジュール「iwasemi OC-β」を発表 | AXIS Web | デザインの視点で、人間の可能性や創造性を伝えるメディア", "published": "2026-02-04 17:17", "ym": "2026-02", "category": "technology", "cat_label": "科技 Technology"}, {"id": 122, "url": "https://www.axismag.jp/posts/2026/02/698014.html", "title": "ZOZO NEXT 新專案「呼色」啟動 發表融合傳統工藝與先端科技的產品原型作品群 | AXIS Web | 以設計觀點傳達人類可能性與創造性的媒體", "orig_title": "ZOZO NEXT新プロジェクト「呼色」始動 伝統工芸と先端技術を融合したプロダクト・プロトタイプ作品群を発表 | AXIS Web | デザインの視点で、人間の可能性や創造性を伝えるメディア", "published": "2026-02-04 14:36", "ym": "2026-02", "category": "product", "cat_label": "產品 Product"}, {"id": 123, "url": "https://www.axismag.jp/posts/2026/02/698406.html", "title": "Chris Liljenberg Halstrøm 在設計與紡織藝術之間往返 | AXIS Web | 以設計觀點傳遞人類可能性與創造性的媒體", "orig_title": "Chris Liljenberg Halstrøm デザインとテキスタイルアートを行き来する | AXIS Web | デザインの視点で、人間の可能性や創造性を伝えるメディア", "published": "2026-02-03 18:08", "ym": "2026-02", "category": "product", "cat_label": "產品 Product"}, {"id": 124, "url": "https://www.axismag.jp/posts/2026/02/698396.html", "title": "Jonas Trampedach 從工藝走向工業的創造之路 | AXIS Web | 以設計視角傳遞人類可能性與創造力的媒體", "orig_title": "Jonas Trampedach クラフトからインダストリアルを生み出す | AXIS Web | デザインの視点で、人間の可能性や創造性を伝えるメディア", "published": "2026-02-03 18:04", "ym": "2026-02", "category": "product", "cat_label": "產品 Product"}, {"id": 125, "url": "https://www.axismag.jp/posts/2026/02/698385.html", "title": "A. Petersen 用時間淬鍊的設計與工藝融合 | AXIS Web | 以設計觀點傳達人類可能性與創造力的媒體", "orig_title": "A. Petersen 時間をかけてつくり出すデザインとクラフトの融合 | AXIS Web | デザインの視点で、人間の可能性や創造性を伝えるメディア", "published": "2026-02-03 18:01", "ym": "2026-02", "category": "product", "cat_label": "產品 Product"}, {"id": 126, "url": "https://www.axismag.jp/posts/2026/02/698082.html", "title": "樂高集團與卡洛馳聯名第一彈「樂高積木涼鞋」上市 | AXIS Web | 以設計觀點傳達人類可能性與創造力的媒體", "orig_title": "レゴグループとクロックスのコラボ第1弾「レゴブロッククロッグ」発売 | AXIS Web | デザインの視点で、人間の可能性や創造性を伝えるメディア", "published": "2026-02-03 17:01", "ym": "2026-02", "category": "product", "cat_label": "產品 Product"}, {"id": 127, "url": "https://www.axismag.jp/posts/2026/02/697797.html", "title": "傳統技術的現代再解讀 福井傳統工藝專案「F-TRAD」發表14項新作 | AXIS Web | 以設計觀點傳達人類可能性與創造力的媒體", "orig_title": "伝統技術を現代に再解釈 福井伝統工芸プロジェクト「F-TRAD」新作14アイテムを発表 | AXIS Web | デザインの視点で、人間の可能性や創造性を伝えるメディア", "published": "2026-02-03 15:24", "ym": "2026-02", "category": "product", "cat_label": "產品 Product"}, {"id": 128, "url": "https://www.axismag.jp/posts/2026/02/697418.html", "title": "雕刻感官的高級訂製服　伊莉絲·范·赫爾彭北美首度個展　在布魯克林美術館舉辦", "orig_title": "感覚を彫刻するクチュール イリス・ヴァン・ヘルペンの北米初個展、ブルックリン美術館で開催 | AXIS Web | デザインの視点で、人間の可能性や創造性を伝えるメディア", "published": "2026-02-03 10:51", "ym": "2026-02", "category": "fashion", "cat_label": "時尚 Fashion"}, {"id": 129, "url": "https://www.axismag.jp/posts/2026/02/697781.html", "title": "FRAMA的裝置藝術展覽「FRAMA VISITS VACANT」 在空間中展示完整產品線", "orig_title": "FRAMAのインスタレーション展示「FRAMA VISITS VACANT」 プロダクトラインを空間全体で紹介 | AXIS Web | デザインの視点で、人間の可能性や創造性を伝えるメディア", "published": "2026-02-02 09:47", "ym": "2026-02", "category": "product", "cat_label": "產品 Product"}, {"id": 130, "url": "https://www.axismag.jp/posts/2026/01/696749.html", "title": "從澀谷字體看見，共創拓展設計的可能性", "orig_title": "シブヤフォントにみる、共創によって拡張されるデザインの可能性 | AXIS Web | デザインの視点で、人間の可能性や創造性を伝えるメディア", "published": "2026-01-30 10:44", "ym": "2026-01", "category": "graphic", "cat_label": "圖像 Graphic"}, {"id": 131, "url": "https://www.axismag.jp/posts/2026/01/697523.html", "title": "茶碗中交鳴的兩種視角 特別展「NIGO®與半泥子」京都舉辦 | AXIS Web | 以設計視角傳遞人類可能性與創造性的媒體", "orig_title": "茶碗で響き合うふたつの視点 特別展「NIGO®と半泥子」京都開催 | AXIS Web | デザインの視点で、人間の可能性や創造性を伝えるメディア", "published": "2026-01-29 15:52", "ym": "2026-01", "category": "craft", "cat_label": "工藝 Craft"}, {"id": 132, "url": "https://www.axismag.jp/posts/2026/01/697430.html", "title": "仲條正義回顧展「歌唱仲條 舞蹈仲條——文字與畫，以及資生堂」於銀座・資生堂藝廊展出 | AXIS Web | 以設計視角傳遞人類可能性與創造力的媒體", "orig_title": "仲條正義回顧展「うたう仲條 おどる仲條 ―文字と画と、資生堂と」 銀座・資生堂ギャラリーで開催 | AXIS Web | デザインの視点で、人間の可能性や創造性を伝えるメディア", "published": "2026-01-29 13:42", "ym": "2026-01", "category": "graphic", "cat_label": "圖像 Graphic"}, {"id": 133, "url": "https://www.axismag.jp/posts/2026/01/697146.html", "title": "照片探問「時尚究竟是什麼」高木由利子「Threads of Beauty 1995–2025」展於澀谷・Bunkamura登場 | AXIS Web | 以設計觀點傳達人類可能性與創造力的媒體", "orig_title": "写真が問いかける“ファッションとは何か” 高木由利子「Threads of Beauty 1995–2025」展が渋谷・Bunkamuraで開催 | AXIS Web | デザインの視点で、人間の可能性や創造性を伝えるメディア", "published": "2026-01-28 14:10", "ym": "2026-01", "category": "art", "cat_label": "藝術 Art"}, {"id": 134, "url": "https://www.axismag.jp/posts/2026/01/697168.html", "title": "索尼推出業界首款耳夾型真無線耳機「LinkBuds Clip」| AXIS Web | 以設計觀點傳達人類可能性與創造力的媒體", "orig_title": "ソニー、イヤーカフ型完全ワイヤレスヘッドホン「LinkBuds Clip」を発売 | AXIS Web | デザインの視点で、人間の可能性や創造性を伝えるメディア", "published": "2026-01-28 12:06", "ym": "2026-01", "category": "product", "cat_label": "產品 Product"}, {"id": 135, "url": "https://www.axismag.jp/posts/2026/01/696592.html", "title": "「誕辰100年 森英恵 維塔爾・類型」展於國立新美術館舉辦 | AXIS Web | 從設計觀點傳遞人類可能性與創造性的媒體", "orig_title": "「生誕100年 森英恵 ヴァイタル・タイプ」展が国立新美術館で開催 | AXIS Web | デザインの視点で、人間の可能性や創造性を伝えるメディア", "published": "2026-01-27 15:56", "ym": "2026-01", "category": "fashion", "cat_label": "時尚 Fashion"}, {"id": 136, "url": "https://www.axismag.jp/posts/2026/01/696773.html", "title": "「LIFE×DESIGN」展在東京Big Sight舉辦 | AXIS Web | 以設計的視角傳達人類的可能性與創造力之媒體", "orig_title": "「LIFE×DESIGN」展が東京ビッグサイトで開催 | AXIS Web | デザインの視点で、人間の可能性や創造性を伝えるメディア", "published": "2026-01-27 12:27", "ym": "2026-01", "category": "product", "cat_label": "產品 Product"}, {"id": 137, "url": "https://www.axismag.jp/posts/2026/01/696887.html", "title": "將玻璃的詩意融入日常 伊肯多夫米蘭 2026年新品系列發表 | AXIS Web | 以設計觀點傳達人類可能性與創造力的媒體", "orig_title": "ガラスの詩情を日常へ イッケンドルフ・ミラノ2026年新作コレクション発表 | AXIS Web | デザインの視点で、人間の可能性や創造性を伝えるメディア", "published": "2026-01-26 16:09", "ym": "2026-01", "category": "product", "cat_label": "產品 Product"}, {"id": 138, "url": "https://www.axismag.jp/posts/2026/01/696901.html", "title": "竹尾「創作者100人賀年卡」展 vol.21　東京・大阪・福岡三地同步展出中 | AXIS Web | 以設計觀點傳達人類的可能性與創造力之媒體", "orig_title": "竹尾「クリエイター100人からの年賀状」展 vol.21 東京・大阪・福岡の３会場で開催中 | AXIS Web | デザインの視点で、人間の可能性や創造性を伝えるメディア", "published": "2026-01-26 10:33", "ym": "2026-01", "category": "graphic", "cat_label": "圖像 Graphic"}, {"id": 139, "url": "https://www.axismag.jp/posts/2026/01/696732.html", "title": "將製作現場本身作為展示 TORQ DESIGN個展「CULTIVATING STUDIO」東京・表參道舉辦中 | AXIS Web | 以設計的觀點，傳達人類的可能性與創造力之媒體", "orig_title": "制作現場そのものを展示 TORQ DESIGN個展「CULTIVATING STUDIO」東京・表参道で開催中 | AXIS Web | デザインの視点で、人間の可能性や創造性を伝えるメディア", "published": "2026-01-23 15:59", "ym": "2026-01", "category": "", "cat_label": ""}, {"id": 140, "url": "https://www.axismag.jp/posts/2026/01/696619.html", "title": "蛇形藝廊展館2026 LANZA atelier獲選 迎接第25屆里程碑的建築實驗場所", "orig_title": "サーペンタイン・パビリオン2026にLANZA atelierが選出 25回目の節目を迎える建築実験の場 | AXIS Web | デザインの視点で、人間の可能性や創造性を伝えるメディア", "published": "2026-01-23 14:20", "ym": "2026-01", "category": "architecture", "cat_label": "建築 Architecture"}, {"id": 141, "url": "https://www.axismag.jp/posts/2026/01/696318.html", "title": "將港湾遺構重新構築的博物館 法國「布里斯・梵港湾博物館」| AXIS Web | 以設計的觀點，傳遞人類的可能性與創造性的媒體", "orig_title": "港湾遺構を再構築した博物館 フランス「ブリーズ・ヴァン港湾ミュージアム」 | AXIS Web | デザインの視点で、人間の可能性や創造性を伝えるメディア", "published": "2026-01-21 16:30", "ym": "2026-01", "category": "architecture", "cat_label": "建築 Architecture"}, {"id": 142, "url": "https://www.axismag.jp/posts/2026/01/696560.html", "title": "生活滋養而生的哥本哈根街道 | AXIS Web | 以設計觀點傳遞人類可能性與創造力的媒體", "orig_title": "暮らしが育てるコペンハーゲンの街 | AXIS Web | デザインの視点で、人間の可能性や創造性を伝えるメディア", "published": "2026-01-21 13:02", "ym": "2026-01", "category": "architecture", "cat_label": "建築 Architecture"}, {"id": 143, "url": "https://www.axismag.jp/posts/2026/01/696575.html", "title": "TAKT 實踐永續發展，更新傳統 | AXIS Web | 以設計觀點傳達人類可能性與創造力的媒體", "orig_title": "TAKT サステナビリティを実践し、伝統を更新する | AXIS Web | デザインの視点で、人間の可能性や創造性を伝えるメディア", "published": "2026-01-21 12:54", "ym": "2026-01", "category": "", "cat_label": ""}, {"id": 144, "url": "https://www.axismag.jp/posts/2026/01/696298.html", "title": "WOOD YOU LIKE COMPANY攜手建築師與設計師共同創作家具與空間的「CO-CRAFT」展覽 | AXIS Web | 以設計視角傳達人類的可能性與創造力", "orig_title": "WOOD YOU LIKE COMPANYが建築家やデザイナーと家具・空間を共作する「CO-CRAFT」Exhibitionを開催 | AXIS Web | デザインの視点で、人間の可能性や創造性を伝えるメディア", "published": "2026-01-21 10:44", "ym": "2026-01", "category": "product", "cat_label": "產品 Product"}, {"id": 145, "url": "https://www.axismag.jp/posts/2026/01/696383.html", "title": "探索藍色相關工藝的可能性 京都藝術大學成果展「出於藍 2025年 藍的學校 阿波篇」| AXIS Web | 以設計視角傳達人類可能性與創造力的媒體", "orig_title": "藍にまつわる工芸のあり方を探る 京都芸術大学成果展「藍より出づ 2025年 藍の學校 阿波篇」開催 | AXIS Web | デザインの視点で、人間の可能性や創造性を伝えるメディア", "published": "2026-01-20 17:13", "ym": "2026-01", "category": "craft", "cat_label": "工藝 Craft"}, {"id": 146, "url": "https://www.axismag.jp/posts/2026/01/696403.html", "title": "即將廢棄的鞋款化身家具 ASICS × Karimoku New Standard 特別聯名款上市 | AXIS Web | 以設計視角傳遞人類可能性與創造力的媒體", "orig_title": "廃棄予定のシューズが家具へ アシックス×Karimoku New Standard特別コラボモデル発売 | AXIS Web | デザインの視点で、人間の可能性や創造性を伝えるメディア", "published": "2026-01-20 17:01", "ym": "2026-01", "category": "product", "cat_label": "產品 Product"}, {"id": 147, "url": "https://www.axismag.jp/posts/2026/01/696185.html", "title": "觸碰報導與藝術融合的攝影展「W. 尤金・史密斯與紐約閣樓時代」於東京都寫真美術館登場", "orig_title": "報道と芸術の融合に触れる写真展 「W. ユージン・スミスとニューヨーク ロフトの時代」が東京都写真美術館で開催 | AXIS Web | デザインの視点で、人間の可能性や創造性を伝えるメディア", "published": "2026-01-20 15:24", "ym": "2026-01", "category": "culture", "cat_label": "文化 Culture"}, {"id": 148, "url": "https://www.axismag.jp/posts/2026/01/696033.html", "title": "耳機與喇叭兼備的「TDM. Neo」 | AXIS Web | 以設計觀點傳遞人類可能性與創造力的媒體", "orig_title": "ヘッドホンにもスピーカーにもなる「TDM. Neo」 | AXIS Web | デザインの視点で、人間の可能性や創造性を伝えるメディア", "published": "2026-01-19 17:33", "ym": "2026-01", "category": "product", "cat_label": "產品 Product"}, {"id": 149, "url": "https://www.axismag.jp/posts/2026/01/696198.html", "title": "將祖父的哲學，融入今日的生活 「The Conran Shop Exclusive」新系列", "orig_title": "祖父の哲学を、いまの暮らしへ 「The Conran Shop Exclusive」新コレクション | AXIS Web | デザインの視点で、人間の可能性や創造性を伝えるメディア", "published": "2026-01-19 15:44", "ym": "2026-01", "category": "interior", "cat_label": "室內 Interior"}, {"id": 150, "url": "https://www.axismag.jp/posts/2026/01/695931.html", "title": "將歷史巴士轉化為公共遊戲空間 北京・昌平區「Old Beijing Bus」", "orig_title": "歴史的バスを公共遊戯空間に 北京・昌平区「Old Beijing Bus」 | AXIS Web | デザインの視点で、人間の可能性や創造性を伝えるメディア", "published": "2026-01-19 13:37", "ym": "2026-01", "category": "architecture", "cat_label": "建築 Architecture"}]}